flare_protobuf_plugin/__init__.py
flare_protobuf_plugin/additional_fields.py
flare_protobuf_plugin/grpc_python_plugin.py
flare_protobuf_plugin/grpclib.lock
flare_protobuf_plugin/mypy_protobuf.lock
flare_protobuf_plugin/protoc_plugins.py
flare_protobuf_plugin/python_protobuf_module_mapper.py
flare_protobuf_plugin/python_protobuf_subsystem.py
flare_protobuf_plugin/register.py
flare_protobuf_plugin/rules.py
flare_protobuf_plugin-0.1.0.dist-info/LICENSE-MIT.txt
flare_protobuf_plugin-0.1.0.dist-info/METADATA
flare_protobuf_plugin-0.1.0.dist-info/WHEEL
flare_protobuf_plugin-0.1.0.dist-info/namespace_packages.txt
flare_protobuf_plugin-0.1.0.dist-info/top_level.txt
flare_protobuf_plugin-0.1.0.dist-info/RECORD
