Metadata-Version: 2.1
Name: flare-protobuf-plugin
Version: 0.1.0
Summary: An extended protobuf plugin for pants build system
Author-email: Israël Hallé <israel.halle@flare.io>
License: MIT License
Keywords: pantsbuild,pants,backend,secrets
Classifier: Development Status :: 4 - Beta
Classifier: Programming Language :: Python
Classifier: Topic :: Software Development :: Build Tools
Requires-Python: ==3.9.*
License-File: LICENSE-MIT.txt
